setup.py
vmcontroller/__init__.py
vmcontroller.host.egg-info/PKG-INFO
vmcontroller.host.egg-info/SOURCES.txt
vmcontroller.host.egg-info/dependency_links.txt
vmcontroller.host.egg-info/entry_points.txt
vmcontroller.host.egg-info/namespace_packages.txt
vmcontroller.host.egg-info/not-zip-safe
vmcontroller.host.egg-info/requires.txt
vmcontroller.host.egg-info/top_level.txt
vmcontroller/host/__init__.py
vmcontroller/host/__main__.py
vmcontroller/host/config/__init__.py
vmcontroller/host/controller/HyperVisorController.py
vmcontroller/host/controller/__init__.py
vmcontroller/host/controller/hypervisors/VirtualBox.py
vmcontroller/host/controller/hypervisors/__init__.py
vmcontroller/host/services/FileTransferClient.py
vmcontroller/host/services/HostServices.py
vmcontroller/host/services/HostStompEngine.py
vmcontroller/host/services/HostWords.py
vmcontroller/host/services/__init__.py